{"activity_counts": null, "config": {"csrf_token": "HQCbEViU4NDht1ERSwbhAdtVz0zJk1Md", "viewer": null}, "country_code": "NL", "language_code": "en", "entry_data": {"TagPage": [{"tag": {"name": "baby", "content_advisory": null, "media": {"nodes": [{"comments_disabled": false, "id": "1516765403849127762", "dimensions": {"height": 1080, "width": 1080}, "owner": {"id": "826191307"}, "thumbnail_src": "https://scontent.cdninstagram.com/t51.2885-15/s640x640/sh0.08/e35/18443275_212041802643923_8687679032520605696_n.jpg", "is_video": false, "code": "BUMohlAB3dS", "date": 1495032547, "display_src": "https://scontent.cdninstagram.com/t51.2885-15/e35/18443275_212041802643923_8687679032520605696_n.jpg", "caption": "\ubbf8\uc138\uba3c\uc9c0\uac00 \uac31\uc7a5\ud788 \ub9ce\uc740 \uc5b4\ub290\ub0a0\n\uc9c0\ub098\uac00\ub358 \ud589\uc7781\ud560\uba38\ub2c8 \uc6b8\uc720\ubaa8\ucc28 \ubcf4\uace0 \uc648\n(\uc190\ub140 \uc7a5\ub09c\uac10 \uc624\ud508\uce74 \ud0dc\uc6b0\uace0 \ubc00\uace0\uac00\uc2dc\uba70)\n\"\uc800\uc544\uc774 \uca84\uc96d\uac83\ub2e4\"\n.....\n\ubbf8\uc138\uba3c\uc9c0 \ub9ce\uc740\ub0a0\uc778\ub370...\n\ud560\uba38\ub2c8 \uc624\ud508\uce74\ub294 \uc880...\n\uc6b0\ub9ac\uc8fc\uc5b4\ub2c8 \uca84\uc8fd\uc5b4\ub3c4 \ubbf8\uc138\uba3c\uc9c0\ub85c \uc8fd\uae30\ub294 \uc2eb\uc740...\n\ubbf8\uc138\uba3c\uc9c0\uac00 \uc9c0\ub098\uac00\uace0 \uc694\uc998 \ubc29\ud48d\ucee4\ubc84 \ubc97\uae30\uace0 \ub2e4\ub2c8\uace0 \uc788\uc74c\uc694 \ub77c\uba70\n\uc9c0\ub098\uac00\ub358 \ud589\uc7781 \ud560\uba38\ub2c8 \ubcf4\uba74 \uaf2d \ud574\ub4dc\ub9ac\uace0 \uc2f6\uc740\ub9d0\uc774\ub124\uc694\ud83e\udd17\n-\n-\n-\n-\n#\ub0a0\uc528\uc88b\uc740 #5\uc6d4 #\uc720\ubaa8\ucc28 #\ubc29\ud48d\ucee4\ubc84 #\uc624\ud508\ud574\uc694 #\ube14\ub7ad\ud0b7 #\ub2e4\uc2dc\ub9cc\ub4e4\uace0\uc2f6\ub2e4 #\ub3c5\ubc15\uc721\uc544 #\uace7 #\uc9c0\ub098\uac00\ub9ac #\uc544\ub4e4\uacfc\uc5c4\ub9c8 #\ub098\ub4e4\uc774 #\uc720\ubaa8\ucc28\ud55c\uc9d0 #\uc6d0\ud53c\uc2a4\ub355\ud6c4 #\ub9d8\uc2a4\ud0c0\uadf8\ub7a8 #\uc721\uc544 #\uc5c4\ub9c8\uc2a4\ud0c0\uadf8\ub7a8 #\uc721\uc544\uc77c\uae30 #\uc721\uc544\uc18c\ud1b5 #\ub77c\uc774\ud504 #\uc77c\uc0c1 #\ub370\uc77c\ub9ac #\uc6d0\ud53c\uc2a4\uc804\ubb38 #dailylook #life #mom #baby #dailyfashion #style #lovebini", "comments": {"count": 0}, "likes": {"count": 0}}, {"comments_disabled": false, "id": "1516765383960136069", "dimensions": {"height": 800, "width": 640}, "owner": {"id": "1544940610"}, "thumbnail_src": "https://scontent.cdninstagram.com/t51.2885-15/s640x640/e15/c0.90.720.720/18444895_276473609489478_1515514515024773120_n.jpg", "is_video": true, "code": "BUMohSejYmF", "date": 1495032545, "display_src": "https://scontent.cdninstagram.com/t51.2885-15/e15/p640x640/18444895_276473609489478_1515514515024773120_n.jpg", "video_views": 0, "caption": "#ritkamoja #baby #myson \ud83d\ude0d\ud83d\ude0d\ud83d\ude0d", "comments": {"count": 0}, "likes": {"count": 0}}, {"comments_disabled": false, "id": "1516765377593092176", "dimensions": {"height": 1350, "width": 1080}, "owner": {"id": "498809373"}, "thumbnail_src": "https://scontent.cdninstagram.com/t51.2885-15/s640x640/sh0.08/e35/c0.135.1080.1080/18513508_769590173204926_2811435525527830528_n.jpg", "is_video": false, "code": "BUMohMjDChQ", "date": 1495032544, "display_src": "https://scontent.cdninstagram.com/t51.2885-15/e35/18513508_769590173204926_2811435525527830528_n.jpg", "caption": "si nengnong kalemmm....\n#nightlife #baby #child #daughter #begadang #foreverything", "comments": {"count": 0}, "likes": {"count": 0}}, {"comments_disabled": false, "id": "1516765369624472938", "dimensions": {"height": 1080, "width": 1080}, "owner": {"id": "1936016964"}, "thumbnail_src": "https://scontent.cdninstagram.com/t51.2885-15/s640x640/sh0.08/e35/18514130_1429062447152980_2186781026800369664_n.jpg", "is_video": false, "code": "BUMohFIFK1q", "date": 1495032543, "display_src": "https://scontent.cdninstagram.com/t51.2885-15/e35/18514130_1429062447152980_2186781026800369664_n.jpg", "caption": "War ein super sch\u00f6ner Abend \ud83d\ude0d\ud83d\udc95 Freue mich schon auf November \ud83d\ude48\n\n#julia #engelmann #juliaengelmann #poetryslam #poetry #slam #kassel #eines #tages #baby #einestagesbaby #einestagesbabywerdenwiraltsein #strichm\u00e4nnchen #2017", "comments": {"count": 0}, "likes": {"count": 0}}, {"comments_disabled": false, "id": "1516765366687159406", "dimensions": {"height": 608, "width": 1080}, "owner": {"id": "1573625068"}, "thumbnail_src": "https://scontent.cdninstagram.com/t51.2885-15/e35/c236.0.608.608/18514151_341559172914167_738096838556516352_n.jpg", "is_video": false, "code": "BUMohCZANRu", "date": 1495032543, "display_src": "https://scontent.cdninstagram.com/t51.2885-15/e35/18514151_341559172914167_738096838556516352_n.jpg", "caption": "#baby#cugino\u2764\ufe0f#", "comments": {"count": 0}, "likes": {"count": 0}}, {"comments_disabled": false, "id": "1516765352209413361", "dimensions": {"height": 1080, "width": 1080}, "owner": {"id": "1932853221"}, "thumbnail_src": "https://scontent.cdninstagram.com/t51.2885-15/s640x640/sh0.08/e35/18512519_1336168819796105_8770457509174444032_n.jpg", "is_video": false, "code": "BUMog06D_Tx", "date": 1495032541, "display_src": "https://scontent.cdninstagram.com/t51.2885-15/e35/18512519_1336168819796105_8770457509174444032_n.jpg", "caption": "As linhas retas da cole\u00e7\u00e3o Linea acompanham o bercinho e deixam o espa\u00e7o alegre e diferenciado.\n\nCom certeza um destaque a parte para a decora\u00e7\u00e3o do quarto do seu beb\u00ea.\n-\nwww.giuly.com.br\n-\n#giulytricot #tricot #tric\u00f4 #kitber\u00e7o #kitber\u00e7otricot #kitsdeber\u00e7o #beb\u00ea #baby #enxovalbebe #enxovaldetricot #enxovaldebebe #kittricot #gravidafeliz #lateralretangular #macio #lojaonline #tricoartesanal #quartomoderninho #quartomoderninhodebebe #kitmoderno #kitprotetordeberco #kitprotetordeber\u00e7o", "comments": {"count": 0}, "likes": {"count": 0}}, {"comments_disabled": false, "id": "1516765351109475352", "dimensions": {"height": 753, "width": 640}, "owner": {"id": "4569033247"}, "thumbnail_src": "https://scontent.cdninstagram.com/t51.2885-15/s640x640/sh0.08/e35/c0.64.720.720/18513418_1290895431028313_2057635307284594688_n.jpg", "is_video": false, "code": "BUMogz4gDwY", "date": 1495032541, "display_src": "https://scontent.cdninstagram.com/t51.2885-15/sh0.08/e35/p640x640/18513418_1290895431028313_2057635307284594688_n.jpg", "caption": "\u0410 \u0443 \u0432\u0430\u0441 \u0442\u0430\u043a \u0436\u0435 ?\ud83d\ude01\u270f\u0412\u0441\u0435 \u043f\u0438\u0448\u0438\u0442\u0435 \u0441\u0432\u043e\u0435 \u043c\u043d\u0435\u043d\u0438\u0435\u270f \u043f\u043e\u0434\u043f\u0438\u0441\u044b\u0432\u0430\u0435\u043c\u0441\u044f \u043d\u0430 \u043d\u0430\u0448\u0438 \u043f\u0440\u043e\u0435\u043a\u0442\u044b  @zoonyus  \u043e\u0442\u043c\u0435\u0447\u0430\u0439\u0442\u0435 \u0441\u0432\u043e\u0438\u0445 \u0434\u0440\u0443\u0437\u0435\u0439\ud83d\udc6c \u2764\u0421\u0442\u0430\u0432\u044c\u0442\u0435 \u043b\u0430\u0439\u043a\u0438 \u2764 \u267b\u041f\u043e\u0434\u043f\u0438\u0441\u044b\u0432\u0430\u0439\u0442\u0435\u0441\u044c \u267b#kids #kid #child #instakids #baby #babies #babiesofinstagram #instagramanet #children #childrenphoto #tiny #little #family #instababy #igbabies #\u0434\u0435\u0442\u0438 #\u0434\u0435\u0442\u0438\u0448\u043a\u0438 #\u0440\u0435\u0431\u0435\u043d\u043e\u043a #\u043e\u0447\u0430\u0440\u043e\u0432\u0430\u0448\u043a\u0438 #\u0443\u043b\u044b\u0431\u043a\u0430 #\u0441\u0435\u043c\u044c\u044f #\u0444\u043e\u0442\u043e\u0434\u0435\u0442\u0438  #\u0441\u043c\u044b\u0441\u043b\u0436\u0438\u0437\u043d\u0438 #\u043c\u043e\u0438\u0434\u0435\u0442\u0438 #\u043c\u043e\u0439\u0440\u0435\u0431\u0435\u043d\u043e\u043a  #\u043b\u044e\u0431\u043b\u044e #\u043b\u044e\u0431\u043e\u0432\u044c\u043c\u043e\u044f #\u0438\u043d\u0441\u0442\u0430\u0433\u0440\u0430\u043c\u0430\u043d\u0435\u0442 #\u043c\u0430\u043b\u044f\u0432\u043a\u0430 #\u043c\u0430\u043b\u043e\u0439", "comments": {"count": 0}, "likes": {"count": 1}}, {"comments_disabled": false, "id": "1516765349088654027", "dimensions": {"height": 1025, "width": 1080}, "owner": {"id": "5372714351"}, "thumbnail_src": "https://scontent.cdninstagram.com/t51.2885-15/s640x640/sh0.08/e35/c27.0.1025.1025/18444731_747444542084383_8132514153999892480_n.jpg", "is_video": false, "code": "BUMogyADPLL", "date": 1495032541, "display_src": "https://scontent.cdninstagram.com/t51.2885-15/e35/18444731_747444542084383_8132514153999892480_n.jpg", "caption": "#cute\ud83d\ude0d #baby ##photo #photos #pic #pics #picture #pictures #snapshot #art #beautiful #instagood #picoftheday #photooftheday #color #all_shots #exposure #composition #focus #capture #moment #l #f....", "comments": {"count": 0}, "likes": {"count": 1}}, {"comments_disabled": false, "id": "1516765344424004941", "dimensions": {"height": 1080, "width": 1080}, "owner": {"id": "455377014"}, "thumbnail_src": "https://scontent.cdninstagram.com/t51.2885-15/s640x640/sh0.08/e35/18444306_295075497613835_9184257215639322624_n.jpg", "is_video": false, "code": "BUMogtqBA1N", "date": 1495032540, "display_src": "https://scontent.cdninstagram.com/t51.2885-15/e35/18444306_295075497613835_9184257215639322624_n.jpg", "caption": "#babygirl #inlove #nina #newborn #4semanas #4week #bebe #babylove #baby #babycute", "comments": {"count": 0}, "likes": {"count": 0}}, {"comments_disabled": false, "id": "1516765341656343735", "dimensions": {"height": 1350, "width": 1080}, "owner": {"id": "2532497299"}, "thumbnail_src": "https://scontent.cdninstagram.com/t51.2885-15/s640x640/sh0.08/e35/c0.135.1080.1080/18580607_1963498733869094_905775870780637184_n.jpg", "is_video": false, "code": "BUMogrFDOS3", "date": 1495032540, "display_src": "https://scontent.cdninstagram.com/t51.2885-15/e35/18580607_1963498733869094_905775870780637184_n.jpg", "caption": "\u5f88\u4e45\u5f88\u4e45\u6c92\u88ab\u5bf5\u5e78\u7684\u73a9\u5177\n\n\u7136\u5f8c\u73a9\u4e8610\u5206\u9418\u5c31\u4e00\u76f4\u5047\u6389\ud83d\ude11\n\n#babygirl #baby #babylife #mom #\u5abd\u5abd\u7684\u8996\u89d2", "comments": {"count": 0}, "likes": {"count": 0}}, {"comments_disabled": false, "id": "1516765335658448950", "dimensions": {"height": 750, "width": 750}, "owner": {"id": "12242825"}, "thumbnail_src": "https://scontent.cdninstagram.com/t51.2885-15/s640x640/sh0.08/e35/18579932_157796068090808_1816969859985047552_n.jpg", "is_video": false, "code": "BUMoglfjEg2", "date": 1495032539, "display_src": "https://scontent.cdninstagram.com/t51.2885-15/e35/18579932_157796068090808_1816969859985047552_n.jpg", "caption": "2\u4eba\u3068\u3082\u53ef\u611b\u3059\u304e\n\n#\u30de\u30de\u5b8c\u6557\n#\u306f\u308b\u306f\u5b8c\u5168\u306b\u81ea\u5206\u306e\u53ef\u611b\u3055\u306b\u6c17\u3065\u3044\u3066\u308b\n#\u660e\u65e5\u306f\u9d28\u5ddd\u30b7\u30fc\u30ef\u30fc\u30eb\u30c9\ud83d\udc2c\n\n#2\u6b73 #2\u6b7310\u30f6\u6708 #\u7537\u306e\u5b50 #\u5b50\u4f9b #\u89aa\u30d0\u30ab #\u89aa\u30d0\u30ab\u90e8 #7\u6708\u751f\u307e\u308c #\u5927\u597d\u304d #\u30b3\u30ba\u30ec #\u30de\u30de\u30ea #\u30b3\u30c9\u30e2\u30ce #\u30d9\u30d3\u30d5\u30eb #\u30b3\u30ce\u30d3\u30fc #ig_kids #instakids #kids #child #love #ig_kidsphoto #\u8d64\u3061\u3083\u3093 #baby #7\u30f6\u6708 #10\u6708\u751f\u307e\u308c #\u5144\u5f1f #2\u6b73\u5dee #\u30b9\u30ce\u30de\u30de #snow", "comments": {"count": 0}, "likes": {"count": 0}}, {"comments_disabled": false, "id": "1516765331782158998", "dimensions": {"height": 1080, "width": 1080}, "owner": {"id": "4795404153"}, "thumbnail_src": "https://scontent.cdninstagram.com/t51.2885-15/s640x640/sh0.08/e35/18580316_1440311102705786_6798438470810337280_n.jpg", "is_video": false, "code": "BUMogh4gMqW", "date": 1495032539, "display_src": "https://scontent.cdninstagram.com/t51.2885-15/e35/18580316_1440311102705786_6798438470810337280_n.jpg", "caption": "#\u751f\u5f8c2\u30f6\u6708 \ud83c\udf82\u2728\n#d61 #\u3042\u3063\u3068\u3044\u3046\u9593\u306b2\u30f6\u6708\u7d4c\u904e #\u6642\u9593\u304c\u7d4c\u3064\u306e\u304c\u65e9\u3044 #\u6210\u9577\u306f\u3082\u3063\u3068\u65e9\u3044 #5870g #58cm #2\u30f6\u6708\u306e\u7bc0\u76ee\u306b\u521d\u3081\u3066\u306e\u3065\u304f\u3057 #\u80b2\u5150\u76f8\u8ac7\u4f1a\u306b\u521d\u53c2\u6226 #\u7279\u306b\u76f8\u8ac7\u3057\u305f\u3044\u3053\u3068\u306a\u304b\u3063\u305f\u3051\u3069 #\u30a2\u30a6\u30a7\u30a4\u611f #\u3051\u3069\u3081\u3052\u305a\u306b\u6765\u6708\u3082\u53c2\u52a0\u4e88\u5b9a #\u80b2\u5150\u76f8\u8ac7\u4f1a #\u8eab\u4f53\u6e2c\u5b9a #\u521d\u3081\u3066\u306e\u4e88\u9632\u63a5\u7a2e #\u30de\u30c3\u30af\u30b9\u6ce3\u304d #hib #b\u578b\u809d\u708e #\u30ed\u30bf\u30a6\u30a3\u30eb\u30b9 #\u4e73\u5150\u7528\u80ba\u708e\u7403\u83cc #\u98f2\u307f\u85ac\u306f\u304c\u3076\u98f2\u307f #\u3042\u3093\u3071\u3093\u307e\u3093\u7d46\u5275\u818f #\u4e88\u9632\u63a5\u7a2e #baby #mommylife #\u80b2\u5150\u65e5\u8a18 #\u6210\u9577\u8a18\u9332\ud83d\udcdd #\u30aa\u30e0\u30c4\u30a2\u30fc\u30c8", "comments": {"count": 0}, "likes": {"count": 0}}, {"comments_disabled": false, "id": "1516765326682838835", "dimensions": {"height": 1350, "width": 1080}, "owner": {"id": "1981449719"}, "thumbnail_src": "https://scontent.cdninstagram.com/t51.2885-15/s640x640/sh0.08/e35/c0.135.1080.1080/18580494_127702024458051_9120717237534064640_n.jpg", "is_video": false, "code": "BUMogdIj1cz", "date": 1495032538, "display_src": "https://scontent.cdninstagram.com/t51.2885-15/e35/18580494_127702024458051_9120717237534064640_n.jpg", "caption": "#metisses#negresse#perfect#good#gold#fiori#polishgirl#goodfriends#bauty#selfiesunday#selfi#naturelle#black#asiangirl#dope#followme#follow#africa#blackandwhite#asiangirl#metisses#negresse#ginven#baby#like4like#team241#africanwoman#sexy#africa#blackandwhite#asiangirl#metisses#negresse#ginven#baby#like4like#team241#africanwoman#sexy#africa#blackandwhite", "comments": {"count": 0}, "likes": {"count": 0}}, {"comments_disabled": false, "id": "1516765320794073984", "dimensions": {"height": 612, "width": 612}, "owner": {"id": "1762827513"}, "thumbnail_src": "https://scontent.cdninstagram.com/t51.2885-15/e15/18512960_128272001062534_3017907445398765568_n.jpg", "is_video": true, "code": "BUMogXpj-uA", "date": 1495032538, "display_src": "https://scontent.cdninstagram.com/t51.2885-15/e15/18512960_128272001062534_3017907445398765568_n.jpg", "video_views": 0, "caption": "\ud83d\ude0d\ud83d\udc67\ud83d\udc36\ud83d\ude0d\n#dogsbeautifull #shitzu #baby #", "comments": {"count": 0}, "likes": {"count": 0}}, {"comments_disabled": false, "id": "1516765320559168260", "dimensions": {"height": 720, "width": 1080}, "owner": {"id": "175547933"}, "thumbnail_src": "https://scontent.cdninstagram.com/t51.2885-15/s640x640/sh0.08/e35/c180.0.720.720/18580037_1701205126560662_2457913679312584704_n.jpg", "is_video": false, "code": "BUMogXbj4sE", "date": 1495032538, "display_src": "https://scontent.cdninstagram.com/t51.2885-15/e35/18580037_1701205126560662_2457913679312584704_n.jpg", "caption": "#ashleymartinphotos #baby #photography #love #family", "comments": {"count": 0}, "likes": {"count": 0}}, {"comments_disabled": false, "id": "1516765320106681801", "dimensions": {"height": 640, "width": 640}, "owner": {"id": "48126401"}, "thumbnail_src": "https://scontent.cdninstagram.com/t51.2885-15/s640x640/sh0.08/e35/18513867_299298453842030_7822091368297136128_n.jpg", "is_video": false, "code": "BUMogXAlyXJ", "date": 1495032537, "display_src": "https://scontent.cdninstagram.com/t51.2885-15/s640x640/sh0.08/e35/18513867_299298453842030_7822091368297136128_n.jpg", "caption": "#babyjacob#baby#love#blessed#bff", "comments": {"count": 0}, "likes": {"count": 1}}, {"comments_disabled": false, "id": "1516765307976744022", "dimensions": {"height": 750, "width": 750}, "owner": {"id": "2298442818"}, "thumbnail_src": "https://scontent.cdninstagram.com/t51.2885-15/s640x640/sh0.08/e35/18512316_1971126983116017_7604147423274860544_n.jpg", "is_video": false, "code": "BUMogLtlvxW", "date": 1495032536, "display_src": "https://scontent.cdninstagram.com/t51.2885-15/s750x750/sh0.08/e35/18512316_1971126983116017_7604147423274860544_n.jpg", "caption": "BONECA LUNA\n\nContatos da lojinha na bio.\n\n#bonecas#bonecasparanicho \n#bonecasdepano#menina\n#maedemenina#decorbaby\n#quartodemenina#instababy\n#instacute#chadebebe\nchadefralfas#baby#babygirl", "comments": {"count": 0}, "likes": {"count": 0}}, {"comments_disabled": false, "id": "1516765303697346833", "dimensions": {"height": 1092, "width": 1080}, "owner": {"id": "2215849847"}, "thumbnail_src": "https://scontent.cdninstagram.com/t51.2885-15/s640x640/sh0.08/e35/c0.6.1080.1080/18513879_423461884691270_3552529856119963648_n.jpg", "is_video": false, "code": "BUMogHuhJER", "date": 1495032535, "display_src": "https://scontent.cdninstagram.com/t51.2885-15/e35/18513879_423461884691270_3552529856119963648_n.jpg", "caption": "Tanti #coloratissimi #vestitini con coprimutandina #boboli in #store! \n#pantaloni tuta #rossi dlsponibili \n#lov #viasanteuplio46 #catania #sicilia #viaetnea #cool #amazing #colour #summer #baby #spedizioniintuttaitalia", "comments": {"count": 0}, "likes": {"count": 1}}], "count": 106360123, "page_info": {"has_next_page": true, "end_cursor": "J0HWRxi4wAAAF0HWRxi1wAAAFiYA"}}, "top_posts": {"nodes": [{"id": "1516750923502076789", "dimensions": {"height": 800, "width": 640}, "owner": {"id": "2236167192"}, "thumbnail_src": "https://scontent.cdninstagram.com/t51.2885-15/e15/c0.80.640.640/18512913_214982099016318_5435659302138281984_n.jpg", "is_video": true, "code": "BUMlO3IFkN1", "date": 1495030821, "display_src": "https://scontent.cdninstagram.com/t51.2885-15/e15/18512913_214982099016318_5435659302138281984_n.jpg", "video_views": 13454, "caption": "\ud83d\udc76\ud83c\udffb \ud83c\udf5d Tag your friends \ud83d\udc47 Repost From: @gemeaslaraeleticia via @yumytime\n-\n-\n-\n-\n-\n#spaghetti #yummy #baby #eat #eatstagram #pasta #cute #cutness #babylove", "comments": {"count": 65}, "likes": {"count": 3289}}, {"id": "1516724144706861892", "dimensions": {"height": 640, "width": 640}, "owner": {"id": "2921811965"}, "thumbnail_src": "https://scontent.cdninstagram.com/t51.2885-15/e15/18579455_160130217856154_5946289737781215232_n.jpg", "is_video": true, "code": "BUMfJLbgrtE", "date": 1495027629, "display_src": "https://scontent.cdninstagram.com/t51.2885-15/e15/18579455_160130217856154_5946289737781215232_n.jpg", "video_views": 30342, "caption": "Follow us @allaboutvoices for more videos like this\n\nOmg cutest thing I've ever seen\nTag your friends\ud83d\udc47\n#allaboutvoices #smule #shawnmendes", "comments": {"count": 126}, "likes": {"count": 7860}}, {"id": "1516736228311992828", "dimensions": {"height": 361, "width": 640}, "owner": {"id": "541448456"}, "thumbnail_src": "https://scontent.cdninstagram.com/t51.2885-15/e15/c156.0.407.407/18512679_1841422506179975_6435233453322534912_n.jpg", "is_video": true, "code": "BUMh5BKgIn8", "date": 1495029069, "display_src": "https://scontent.cdninstagram.com/t51.2885-15/s640x640/e15/18512679_1841422506179975_6435233453322534912_n.jpg", "video_views": 5774, "caption": "\"\u00dcr\u0259yia\u00e7\u0131q\" Adelina. \ud83d\udc71\u2764\ud83e\udd17 P.S. Sofiya \ud83d\udc71 \u00f6z pay\u0131n\u0131 yeyib qurtarm\u0131\u015fd\u0131r. \ud83c\udf4a\u261d\ud83d\ude0a Amma g\u00f6r\u00fcn\u00fcr ki, g\u00f6z\u00fc bac\u0131s\u0131n\u0131n pay\u0131nda qalm\u0131\u015fd\u0131r. \ud83d\udc40 #sofiya #adelina #amazing #sweet #angel #princess #baby #babytwins #babyfashion #babymodel #babyvideo #twinsvideo #dadoftwins #azeribloggers #aztagram #baku #azerbaijan #whp", "comments": {"count": 70}, "likes": {"count": 2051}}, {"id": "1516116943680253269", "dimensions": {"height": 1350, "width": 1080}, "owner": {"id": "1574592249"}, "thumbnail_src": "https://scontent.cdninstagram.com/t51.2885-15/s640x640/sh0.08/e35/c0.135.1080.1080/18444069_1775713579408921_9014265218972254208_n.jpg", "is_video": false, "code": "BUKVFPaAy1V", "date": 1494955245, "display_src": "https://scontent.cdninstagram.com/t51.2885-15/e35/18444069_1775713579408921_9014265218972254208_n.jpg", "caption": "\u00a1UN GENIO!\ud83c\udf7cF\u00e9lix Conti ya toma la mamadera solito. \ud83d\udc76\ud83d\udcaa\ud83d\udc4f #GenteOnLine #GusConti #XimenaCapristo #FelixConti #Morfable #Baby #InstaBaby #Love #Family", "comments": {"count": 75}, "likes": {"count": 4495}}, {"id": "1516469688884018979", "dimensions": {"height": 937, "width": 750}, "owner": {"id": "1317208990"}, "thumbnail_src": "https://scontent.cdninstagram.com/t51.2885-15/s640x640/sh0.08/e35/c0.101.810.810/18512454_142553039621558_7855453853913710592_n.jpg", "is_video": false, "code": "BULlSW-lD8j", "date": 1494997295, "display_src": "https://scontent.cdninstagram.com/t51.2885-15/sh0.08/e35/p750x750/18512454_142553039621558_7855453853913710592_n.jpg", "caption": "Iss bacche Ka baap #swag hai.\nAur iski maa hai #jackieshroff.\n#baby #swagbaby", "comments": {"count": 17}, "likes": {"count": 4121}}, {"id": "1516726747566124111", "dimensions": {"height": 1144, "width": 1080}, "owner": {"id": "2223948666"}, "thumbnail_src": "https://scontent.cdninstagram.com/t51.2885-15/s640x640/sh0.08/e35/c0.32.1080.1080/18513342_301241063650148_8776311463699546112_n.jpg", "is_video": false, "code": "BUMfvDiAyxP", "date": 1495027939, "display_src": "https://scontent.cdninstagram.com/t51.2885-15/e35/18513342_301241063650148_8776311463699546112_n.jpg", "caption": "Big and little \ud83d\udc96 from: @mini.dash.delilah #doubletrouble", "comments": {"count": 45}, "likes": {"count": 3619}}, {"id": "1516734397365570281", "dimensions": {"height": 1080, "width": 1080}, "owner": {"id": "1404815318"}, "thumbnail_src": "https://scontent.cdninstagram.com/t51.2885-15/s640x640/sh0.08/e35/18512435_1729404950408941_5585623711685279744_n.jpg", "is_video": false, "code": "BUMheX9l0rp", "date": 1495028851, "display_src": "https://scontent.cdninstagram.com/t51.2885-15/e35/18512435_1729404950408941_5585623711685279744_n.jpg", "caption": "\u5199\u771f\u30d0\u30fc\u30b8\u30e7\u30f3\n1\u679a\u76ee\u306e\u9678\u3061\u3083\u3093\u306e\u304a\u76ee\u76ee\u3059\u3054\u3063\ud83d\ude33\u7b11\n\u76ee\u3092\u30ae\u30e5\u30c3\u3066\u9589\u3058\u3066\u958b\u3051\u308b\u3068\u30af\u30c3\u30ad\u30ea\u4e8c\u91cd\u306b\u306a\u308b\u3068\u77e5\u3063\u3066\u3084\u3063\u3066\u3044\u307e\u3057\u305f\ud83d\ude02\n\u30fb\n\u3010\u4eca\u65e5\u306e\u9678\u3061\u3083\u3093\u3011\n\u2764\ufe0e\u3053\u3053\u3061\u3083\u3093\u3092\u898b\u3066\n\u300c\u306a\u3093\u3067\u3053\u3093\u306a\u306b\u53ef\u611b\u3044\u5b50\u304c\u7523\u307e\u308c\u3061\u3083\u3063\u305f\u3093\u3060\u308d\u3046\u306d\u3063\ud83d\ude29\ud83d\udc95\u300d\u2190\u7206\u7b11\n\u2764\ufe0e\u300c\u3053\u3053\u306a\u3061\u3083\u3093\u3068\u7d50\u5a5a\u3059\u308b\u306d\ud83d\udc92\u300d\n\u305d\u308c\u306f\u7121\u7406\u3060\u3068\u4f1d\u3048\u307e\u3057\u305f\ud83d\ude4f\n\u2764\ufe0e\u9678\u3061\u3083\u3093\u304c\u304a\u98a8\u5442\u306b\u5165\u3063\u3066\u3044\u308b\u9593\u306b\u3053\u3053\u3061\u3083\u3093\u304c\u5c31\u5bdd\u3057\u305f\u3089\u3001\u53f7\u6ce3\ud83d\ude22\n\u2764\ufe0e\u300c\u3059\u30fc\u3061\u3083\u3093\uff01\u624b\u3092\u6d17\u3063\u3066\u304b\u3089\u3053\u3053\u3061\u3083\u3093\u89e6\u3063\u3066\u2757\ufe0f\u300d\n\u2026\u3059\u30fc\u3061\u3083\u3093\u306b\u53b3\u3057\u3081\u3067\u3057\u305f\ud83d\ude02", "comments": {"count": 24}, "likes": {"count": 1909}}, {"id": "1516721371988034897", "dimensions": {"height": 1349, "width": 1080}, "owner": {"id": "1799492567"}, "thumbnail_src": "https://scontent.cdninstagram.com/t51.2885-15/s640x640/sh0.08/e35/c0.134.1080.1080/18444225_791709264344879_2443850740909735936_n.jpg", "is_video": false, "code": "BUMeg1IlwVR", "date": 1495027298, "display_src": "https://scontent.cdninstagram.com/t51.2885-15/e35/18444225_791709264344879_2443850740909735936_n.jpg", "caption": "Baby | Beard \u0026 Ink \ud83d\ude18\ud83d\udc4c #cute\n____\n- Model: @welovekaani\n____\nTag us to be featured. \u270c\n#beardedlife_style #beards #bearded #beardgang #baby #family #beard #beardandtattoos #ink #inked #tattoos #tattooed #instabeard #cute", "comments": {"count": 15}, "likes": {"count": 2911}}, {"id": "1516750436357789278", "dimensions": {"height": 750, "width": 750}, "owner": {"id": "638839951"}, "thumbnail_src": "https://scontent.cdninstagram.com/t51.2885-15/s640x640/sh0.08/e35/18444160_453535141659492_2869288490191814656_n.jpg", "is_video": false, "code": "BUMlHxcBlZe", "date": 1495030763, "display_src": "https://scontent.cdninstagram.com/t51.2885-15/s750x750/sh0.08/e35/18444160_453535141659492_2869288490191814656_n.jpg", "caption": "\u60aa\u622f\u3063\u5b50\u306f\u540d\u524d\u3092\u547c\u3070\u308c\u3066\u3053\u306e\u7b11\u9854\u3067\u99c6\u3051\u5bc4\u3063\u3066\u304f\u308b\ud83d\ude39\n\n\u6383\u9664\u6a5f\u30ac\u30c1\u30e3\u30ac\u30c1\u30e3\u3059\u308b\u3068\u30d1\u30d1\u306b\u6012\u3089\u308c\u308b\u3093\u3060\u3088\ud83e\udd17\u7b11\n\n\u30de\u30de\u306f\u58ca\u308c\u305f\u3089\u58ca\u308c\u305f\u6642\u8003\u3048\u308b\u304b\u3089\u3042\u3093\u307e\u308a\u6012\u3089\u306a\u3044\u3051\u3069\u3053\u308c\u3086\u3063\u305f\u3089\u30de\u30de\u3082\u30d1\u30d1\u306b\u6012\u3089\u308c\u308b\u3093\u3060\u306a\ud83e\udd17\ud83d\ude4c\ud83c\udffb\u7b11 .\n.\n.\n#babygirl#japanesegirl#baby#\u30d9\u30d3\u30d5\u30eb#\u30de\u30de\u30ea#mamagirl#love", "comments": {"count": 4}, "likes": {"count": 936}}]}}}]}, "gatekeepers": {"bn": true, "ld": true, "pl": true}, "qe": {"ebd": {"g": "", "p": {}}, "create": {"g": "", "p": {}}, "disc": {"g": "", "p": {}}, "feed": {"g": "", "p": {}}, "gql": {"g": "", "p": {}}, "su_universe": {"g": "", "p": {}}, "us": {"g": "", "p": {}}, "us_li": {"g": "", "p": {}}, "nav": {"g": "", "p": {}}, "nav_lo": {"g": "", "p": {}}, "poe": {"g": "", "p": {}}, "pm": {"g": "", "p": {}}, "profile": {"g": "", "p": {}}, "deact": {"g": "", "p": {}}, "sidecar": {"g": "", "p": {}}, "ufi": {"g": "", "p": {}}, "ufi_loggedout": {"g": "", "p": {}}, "video": {"g": "", "p": {}}}, "hostname": "www.instagram.com", "display_properties_server_guess": {"pixel_ratio": 1.5, "viewport_width": 360}, "environment_switcher_visible_server_guess": true, "platform": "web", "probably_has_app": false, "show_app_install": true}