{"activity_counts": null, "config": {"csrf_token": "3xSOwpCmpKEMKt0zqRtJiffTKueApv1u", "viewer": null}, "country_code": "NL", "language_code": "en", "entry_data": {"TagPage": [{"tag": {"name": "oct", "content_advisory": null, "media": {"nodes": [{"comments_disabled": false, "id": "1516740650804194918", "dimensions": {"height": 226, "width": 320}, "owner": {"id": "5443759367"}, "thumbnail_src": "https://scontent.cdninstagram.com/t51.2885-15/e35/c47.0.226.226/18514188_152422231963841_8606789873325572096_n.jpg", "is_video": false, "code": "BUMi5X7lC5m", "date": 1495029597, "display_src": "https://scontent.cdninstagram.com/t51.2885-15/e35/18514188_152422231963841_8606789873325572096_n.jpg", "caption": "#halloween #oct #october #30 #scary #spooky #boo #scared #costume #ghost #pumpkin #pumpkins #pumpkinpatch #carving #candy #orange #jackolantern #creepy #fall #trickortreat #trick #treat #instagood #party #holiday #celebrate #bestoftheday #hauntedhouse #haunted", "comments": {"count": 1}, "likes": {"count": 44}}, {"comments_disabled": false, "id": "1516728279527342731", "dimensions": {"height": 640, "width": 640}, "owner": {"id": "1393369421"}, "thumbnail_src": "https://scontent.cdninstagram.com/t51.2885-15/s640x640/sh0.08/e35/18580173_467380773653832_1151368444432613376_n.jpg", "is_video": false, "code": "BUMgFWSBEKL", "date": 1495028122, "display_src": "https://scontent.cdninstagram.com/t51.2885-15/s640x640/sh0.08/e35/18580173_467380773653832_1151368444432613376_n.jpg", "caption": "\ud83c\udf42 \ud83c\udf83 \u2744\ufe0f #cold #toocold #rainyday #toptags @top.tags #coldweather #itscold #coldaf #coldday #freddo #halloween #oct #october #31 #scary #trickortreat #boo #scared #costume #autumn #leaves #fall #falltime #season #seasons #instafall #instagood #instaautumn", "comments": {"count": 0}, "likes": {"count": 15}}, {"comments_disabled": false, "id": "1516716633631318660", "dimensions": {"height": 746, "width": 640}, "owner": {"id": "1393369421"}, "thumbnail_src": "https://scontent.cdninstagram.com/t51.2885-15/s640x640/sh0.08/e35/c0.60.720.720/18445036_1101627559937952_5087478793216458752_n.jpg", "is_video": false, "code": "BUMdb4MhWKE", "date": 1495026734, "display_src": "https://scontent.cdninstagram.com/t51.2885-15/sh0.08/e35/p640x640/18445036_1101627559937952_5087478793216458752_n.jpg", "caption": "\ud83c\udf42 \ud83c\udf83 \u2744\ufe0f #cold #toocold #rainyday #toptags @top.tags #coldweather #itscold #coldaf #coldday #freddo #halloween #oct #october #31 #scary #trickortreat #boo #scared #costume #autumn #leaves #fall #falltime #season #seasons #instafall #instagood #instaautumn", "comments": {"count": 0}, "likes": {"count": 19}}, {"comments_disabled": false, "id": "1516716440408235764", "dimensions": {"height": 640, "width": 640}, "owner": {"id": "1393369421"}, "thumbnail_src": "https://scontent.cdninstagram.com/t51.2885-15/s640x640/sh0.08/e35/18445036_316801032088591_6094367204986322944_n.jpg", "is_video": false, "code": "BUMdZEPhx70", "date": 1495026711, "display_src": "https://scontent.cdninstagram.com/t51.2885-15/s640x640/sh0.08/e35/18445036_316801032088591_6094367204986322944_n.jpg", "caption": "\ud83c\udf42 \ud83c\udf83 \u2744\ufe0f #cold #toocold #rainyday #toptags @top.tags #coldweather #itscold #coldaf #coldday #freddo #halloween #oct #october #31 #scary #trickortreat #boo #scared #costume #autumn #leaves #fall #falltime #season #seasons #instafall #instagood #instaautumn", "comments": {"count": 0}, "likes": {"count": 11}}, {"comments_disabled": false, "id": "1516712536970766148", "dimensions": {"height": 640, "width": 640}, "owner": {"id": "1393369421"}, "thumbnail_src": "https://scontent.cdninstagram.com/t51.2885-15/s640x640/sh0.08/e35/18444406_1685281915108511_5836801452219039744_n.jpg", "is_video": false, "code": "BUMcgQ4hidE", "date": 1495026245, "display_src": "https://scontent.cdninstagram.com/t51.2885-15/s640x640/sh0.08/e35/18444406_1685281915108511_5836801452219039744_n.jpg", "caption": "\ud83c\udf42 \ud83c\udf83 \u2744\ufe0f #cold #toocold #rainyday #toptags @top.tags #coldweather #itscold #coldaf #coldday #freddo #halloween #oct #october #31 #scary #trickortreat #boo #scared #costume #autumn #leaves #fall #falltime #season #seasons #instafall #instagood #instaautumn", "comments": {"count": 0}, "likes": {"count": 17}}, {"comments_disabled": false, "id": "1516702670097110767", "dimensions": {"height": 480, "width": 480}, "owner": {"id": "1393369421"}, "thumbnail_src": "https://scontent.cdninstagram.com/t51.2885-15/e35/18512606_1692788877681536_3325061838298677248_n.jpg", "is_video": false, "code": "BUMaQrpBlbv", "date": 1495025069, "display_src": "https://scontent.cdninstagram.com/t51.2885-15/s480x480/e35/18512606_1692788877681536_3325061838298677248_n.jpg", "caption": "Joy of going to work every morning\n\ud83c\udf42 \ud83c\udf83 \u2744\ufe0f #cold #toocold #rainyday #toptags @top.tags #coldweather #itscold #coldaf #coldday #freddo #halloween #oct #october #31 #scary #trickortreat #boo #scared #costume #autumn #leaves #fall #falltime #season #seasons #instafall #instagood #instaautumn", "comments": {"count": 0}, "likes": {"count": 5}}, {"comments_disabled": false, "id": "1516702264080073507", "dimensions": {"height": 690, "width": 640}, "owner": {"id": "1393369421"}, "thumbnail_src": "https://scontent.cdninstagram.com/t51.2885-15/s640x640/sh0.08/e35/c0.28.720.720/18382353_1705269073109081_7411567682497019904_n.jpg", "is_video": false, "code": "BUMaKxghgMj", "date": 1495025021, "display_src": "https://scontent.cdninstagram.com/t51.2885-15/sh0.08/e35/p640x640/18382353_1705269073109081_7411567682497019904_n.jpg", "caption": "Colors\n\ud83c\udf42 \ud83c\udf83 \u2744\ufe0f #cold #toocold #rainyday #toptags @top.tags #coldweather #itscold #coldaf #coldday #freddo #halloween #oct #october #31 #scary #trickortreat #boo #scared #costume #autumn #leaves #fall #falltime #season #seasons #instafall #instagood #instaautumn", "comments": {"count": 0}, "likes": {"count": 22}}, {"comments_disabled": false, "id": "1516701431695408281", "dimensions": {"height": 640, "width": 640}, "owner": {"id": "1393369421"}, "thumbnail_src": "https://scontent.cdninstagram.com/t51.2885-15/s640x640/sh0.08/e35/18512415_1188412047972148_404970804187496448_n.jpg", "is_video": false, "code": "BUMZ-qSh_yZ", "date": 1495024921, "display_src": "https://scontent.cdninstagram.com/t51.2885-15/s640x640/sh0.08/e35/18512415_1188412047972148_404970804187496448_n.jpg", "caption": "Perfect getaway\n\ud83c\udf42 \ud83c\udf83 \u2744\ufe0f #cold #toocold #rainyday #toptags @top.tags #coldweather #itscold #coldaf #coldday #freddo #halloween #oct #october #31 #scary #trickortreat #boo #scared #costume #autumn #leaves #fall #falltime #season #seasons #instafall #instagood #instaautumn", "comments": {"count": 0}, "likes": {"count": 27}}, {"comments_disabled": false, "id": "1516700954693923699", "dimensions": {"height": 760, "width": 640}, "owner": {"id": "1393369421"}, "thumbnail_src": "https://scontent.cdninstagram.com/t51.2885-15/s640x640/sh0.08/e35/c0.67.720.720/18512348_809310249227412_8515708314355499008_n.jpg", "is_video": false, "code": "BUMZ3uDBvNz", "date": 1495024864, "display_src": "https://scontent.cdninstagram.com/t51.2885-15/sh0.08/e35/p640x640/18512348_809310249227412_8515708314355499008_n.jpg", "caption": "Leaves everywhere \ud83c\udf42 \ud83c\udf83 \u2744\ufe0f #cold #toocold #rainyday #toptags @top.tags #coldweather #itscold #coldaf #coldday #freddo #halloween #oct #october #31 #scary #trickortreat #boo #scared #costume #autumn #leaves #fall #falltime #season #seasons #instafall #instagood #instaautumn", "comments": {"count": 1}, "likes": {"count": 19}}, {"comments_disabled": false, "id": "1516700663147685553", "dimensions": {"height": 705, "width": 640}, "owner": {"id": "1393369421"}, "thumbnail_src": "https://scontent.cdninstagram.com/t51.2885-15/s640x640/sh0.08/e35/c0.37.720.720/18580286_332065997213631_9074805390054522880_n.jpg", "is_video": false, "code": "BUMZzehhGax", "date": 1495024830, "display_src": "https://scontent.cdninstagram.com/t51.2885-15/sh0.08/e35/p640x640/18580286_332065997213631_9074805390054522880_n.jpg", "caption": "Rainy days \ufe0f #cold #toocold #rainyday #toptags @top.tags #coldweather #itscold #coldaf #coldday #freddo #halloween #oct #october #31 #scary #trickortreat #boo #scared #costume #autumn #leaves #fall #falltime #season #seasons #instafall #instagood #instaautumn", "comments": {"count": 0}, "likes": {"count": 27}}, {"comments_disabled": false, "id": "1516700438735655642", "dimensions": {"height": 640, "width": 640}, "owner": {"id": "1393369421"}, "thumbnail_src": "https://scontent.cdninstagram.com/t51.2885-15/s640x640/sh0.08/e35/18580492_424957554534131_6027680789674590208_n.jpg", "is_video": false, "code": "BUMZwNhhJLa", "date": 1495024803, "display_src": "https://scontent.cdninstagram.com/t51.2885-15/s640x640/sh0.08/e35/18580492_424957554534131_6027680789674590208_n.jpg", "caption": "Sweet cherry pie\n#cold #toocold #rainyday #toptags @top.tags #coldweather #itscold #coldaf #coldday #freddo #halloween #oct #october #31 #scary #trickortreat #boo #scared #costume #autumn #leaves #fall #falltime #season #seasons #instafall #instagood #instaautumn", "comments": {"count": 0}, "likes": {"count": 16}}, {"comments_disabled": false, "id": "1516634836105140337", "dimensions": {"height": 1080, "width": 1080}, "owner": {"id": "1422261753"}, "thumbnail_src": "https://scontent.cdninstagram.com/t51.2885-15/s640x640/sh0.08/e35/18513047_446118949073448_1244647068153151488_n.jpg", "is_video": false, "code": "BUMK1kUB5hx", "date": 1495016983, "display_src": "https://scontent.cdninstagram.com/t51.2885-15/e35/18513047_446118949073448_1244647068153151488_n.jpg", "caption": "#halloween #oct #october #31 #scary #spooky #boo #scared #costume #ghost #pumpkin #pumpkins #pumpkinpatch #carving #candy #orange #jackolantern #creepy #fall #trickortreat #trick #treat #instagood #party #holiday #celebrate #bestoftheday #hauntedhouse #haunted", "comments": {"count": 1}, "likes": {"count": 272}}, {"comments_disabled": false, "id": "1516624090844028032", "dimensions": {"height": 480, "width": 480}, "owner": {"id": "4300404452"}, "thumbnail_src": "https://scontent.cdninstagram.com/t51.2885-15/e35/18513165_248203452324304_6868340154474430464_n.jpg", "is_video": false, "code": "BUMIZNAjtyA", "date": 1495015702, "display_src": "https://scontent.cdninstagram.com/t51.2885-15/s480x480/e35/18513165_248203452324304_6868340154474430464_n.jpg", "caption": "\ud83c\udf83 #halloween #oct @top.tags #october #toptags #31 #scary #trickortreat #boo #scared #costume #ghost #pumpkin #pumpkins #pumpkinpatch #carving #candy #orange #jackolantern #creepy #fall #trick #treat #instagood #party #holiday #celebrate #bestoftheday #hauntedhouse #spooky #haunted", "comments": {"count": 0}, "likes": {"count": 14}}, {"comments_disabled": false, "id": "1516611087445173683", "dimensions": {"height": 1080, "width": 1080}, "owner": {"id": "1386432568"}, "thumbnail_src": "https://scontent.cdninstagram.com/t51.2885-15/s640x640/sh0.08/e35/18512645_295562397547815_2131671777439383552_n.jpg", "is_video": false, "code": "BUMFb-plqWz", "date": 1495014151, "display_src": "https://scontent.cdninstagram.com/t51.2885-15/e35/18512645_295562397547815_2131671777439383552_n.jpg", "caption": "6:30 am views #oct #goldPISS", "comments": {"count": 1}, "likes": {"count": 119}}], "count": 354257, "page_info": {"has_next_page": true, "end_cursor": "J0HWRxZbgAAAF0HWRwbBwAAAFiYA"}}, "top_posts": {"nodes": [{"id": "1516377346574918816", "dimensions": {"height": 576, "width": 480}, "owner": {"id": "335808878"}, "thumbnail_src": "https://scontent.cdninstagram.com/t51.2885-15/e35/c0.50.500.500/18513335_342628416152937_734736185561186304_n.jpg", "is_video": false, "code": "BULQSmgDCSg", "date": 1494986287, "display_src": "https://scontent.cdninstagram.com/t51.2885-15/e35/p480x480/18513335_342628416152937_734736185561186304_n.jpg", "caption": "Toms River North's Craig Larsen pitched a complete game tonight against Toms River South to help the Mariners advance to the OCT Finals to defend their 2016 Title.  #trnorth #mariners #baseball #junior #pitcher #oct #titletown #tr @craig_larsen", "comments": {"count": 9}, "likes": {"count": 220}}, {"id": "1515201465522015345", "dimensions": {"height": 480, "width": 480}, "owner": {"id": "4682991095"}, "thumbnail_src": "https://scontent.cdninstagram.com/t51.2885-15/e35/18443100_264474553958404_5199925125834604544_n.jpg", "is_video": false, "code": "BUHE7R7l0xx", "date": 1494846111, "display_src": "https://scontent.cdninstagram.com/t51.2885-15/s480x480/e35/18443100_264474553958404_5199925125834604544_n.jpg", "caption": "#Me #Oct \ud83d\ude0d comnts ur bornmonth  jinka same hai wo chat kro ekduje se\ud83d\ude09\n#cute_crush_feelings", "comments": {"count": 47}, "likes": {"count": 787}}, {"id": "1516611087445173683", "dimensions": {"height": 1080, "width": 1080}, "owner": {"id": "1386432568"}, "thumbnail_src": "https://scontent.cdninstagram.com/t51.2885-15/s640x640/sh0.08/e35/18512645_295562397547815_2131671777439383552_n.jpg", "is_video": false, "code": "BUMFb-plqWz", "date": 1495014151, "display_src": "https://scontent.cdninstagram.com/t51.2885-15/e35/18512645_295562397547815_2131671777439383552_n.jpg", "caption": "6:30 am views #oct #goldPISS", "comments": {"count": 1}, "likes": {"count": 119}}, {"id": "1516634836105140337", "dimensions": {"height": 1080, "width": 1080}, "owner": {"id": "1422261753"}, "thumbnail_src": "https://scontent.cdninstagram.com/t51.2885-15/s640x640/sh0.08/e35/18513047_446118949073448_1244647068153151488_n.jpg", "is_video": false, "code": "BUMK1kUB5hx", "date": 1495016983, "display_src": "https://scontent.cdninstagram.com/t51.2885-15/e35/18513047_446118949073448_1244647068153151488_n.jpg", "caption": "#halloween #oct #october #31 #scary #spooky #boo #scared #costume #ghost #pumpkin #pumpkins #pumpkinpatch #carving #candy #orange #jackolantern #creepy #fall #trickortreat #trick #treat #instagood #party #holiday #celebrate #bestoftheday #hauntedhouse #haunted", "comments": {"count": 1}, "likes": {"count": 272}}, {"id": "1516209371183529499", "dimensions": {"height": 779, "width": 750}, "owner": {"id": "1743915132"}, "thumbnail_src": "https://scontent.cdninstagram.com/t51.2885-15/s640x640/sh0.08/e35/c0.16.810.810/18445084_440296752987537_3428387000409915392_n.jpg", "is_video": false, "code": "BUKqGPOgz4b", "date": 1494966263, "display_src": "https://scontent.cdninstagram.com/t51.2885-15/sh0.08/e35/p750x750/18445084_440296752987537_3428387000409915392_n.jpg", "caption": "#elforsan_gim#oct", "comments": {"count": 4}, "likes": {"count": 64}}, {"id": "1514772796973928158", "dimensions": {"height": 750, "width": 750}, "owner": {"id": "2195324986"}, "thumbnail_src": "https://scontent.cdninstagram.com/t51.2885-15/s640x640/sh0.08/e35/18444184_626017050926853_6822678402940534784_n.jpg", "is_video": false, "code": "BUFjdVPDk7e", "date": 1494795010, "display_src": "https://scontent.cdninstagram.com/t51.2885-15/s750x750/sh0.08/e35/18444184_626017050926853_6822678402940534784_n.jpg", "caption": "Perempuan diambil dari tulang rusuk laki laki karna tulang rusuk laki laki dekat dengan hati dan tangan,hati untuk mencintai perempuan dan tangan untuk melindungi perempuan.", "comments": {"count": 12}, "likes": {"count": 741}}, {"id": "1515931271095496913", "dimensions": {"height": 937, "width": 750}, "owner": {"id": "2279841709"}, "thumbnail_src": "https://scontent.cdninstagram.com/t51.2885-15/s640x640/sh0.08/e35/c0.125.999.999/18513797_1048001785335874_6351343387592884224_n.jpg", "is_video": false, "code": "BUJq3WVjbDR", "date": 1494933111, "display_src": "https://scontent.cdninstagram.com/t51.2885-15/sh0.08/e35/p750x750/18513797_1048001785335874_6351343387592884224_n.jpg", "caption": "Que t\u00e1 experimentar nosso delicioso card\u00e1pio do Almo\u00e7o executivo? \ud83d\ude0dCorre pra Vanilla e experimente nossas del\u00edcias. .\n.\n.\n.\n#sudoeste #oct #octogonal #brasilia #bsb #brigadeiro #almoco #almo\u00e7o #terracoshopping #ter\u00e7a #vanillabrigaderia #vanillacafetetia #vanillacafe #vanilla", "comments": {"count": 9}, "likes": {"count": 168}}, {"id": "1513745563665053013", "dimensions": {"height": 1080, "width": 1080}, "owner": {"id": "3207474890"}, "thumbnail_src": "https://scontent.cdninstagram.com/t51.2885-15/s640x640/sh0.08/e35/18443678_190118214843796_9030415124933902336_n.jpg", "is_video": false, "code": "BUB55HqlDVV", "date": 1494672554, "display_src": "https://scontent.cdninstagram.com/t51.2885-15/e35/18443678_190118214843796_9030415124933902336_n.jpg", "caption": "#halloween #oct #october #30 #scary #spooky #boo #scared #costume #ghost #pumpkin #pumpkins #pumpkinpatch #carving #candy #orange #jackolantern #creepy #fall #trickortreat #trick #treat #instagood #party #holiday #celebrate #bestoftheday #hauntedhouse #haunted", "comments": {"count": 10}, "likes": {"count": 3286}}, {"id": "1515007093832105610", "dimensions": {"height": 1080, "width": 1080}, "owner": {"id": "226135459"}, "thumbnail_src": "https://scontent.cdninstagram.com/t51.2885-15/s640x640/sh0.08/e35/18444215_738862082960940_1903335493324505088_n.jpg", "is_video": false, "code": "BUGYuzMDz6K", "date": 1494822941, "display_src": "https://scontent.cdninstagram.com/t51.2885-15/e35/18444215_738862082960940_1903335493324505088_n.jpg", "caption": "Its a boy!!!! We can't wait to meet you little one ! My baby boy is going to be a Junior !! #AlreadyAProudDaddy #WeLoveYou #BabyFootballTeam #Oct.4", "comments": {"count": 3}, "likes": {"count": 105}}]}}}]}, "gatekeepers": {"bn": true, "ld": true, "pl": true}, "qe": {"ebd": {"g": "holdout", "p": {"use_new_styles": "false"}}, "create": {"g": "", "p": {}}, "disc": {"g": "", "p": {}}, "feed": {"g": "", "p": {}}, "gql": {"g": "", "p": {}}, "su_universe": {"g": "", "p": {}}, "us": {"g": "", "p": {}}, "us_li": {"g": "", "p": {}}, "nav": {"g": "", "p": {}}, "nav_lo": {"g": "", "p": {}}, "poe": {"g": "try_email_and_phone_login_control_05", "p": {"show_phone_or_email_text": "false", "try_email_and_phone_login": "false"}}, "pm": {"g": "", "p": {}}, "profile": {"g": "", "p": {}}, "deact": {"g": "", "p": {}}, "sidecar": {"g": "", "p": {}}, "ufi": {"g": "", "p": {}}, "ufi_loggedout": {"g": "control_20170411", "p": {"is_enabled": "false"}}, "video": {"g": "", "p": {}}}, "hostname": "www.instagram.com", "display_properties_server_guess": {"pixel_ratio": 1.5, "viewport_width": 360}, "environment_switcher_visible_server_guess": true, "platform": "web", "probably_has_app": false, "show_app_install": true}