{"activity_counts": null, "config": {"csrf_token": "qXBDBe8OTFkNQ95u0I8NqreO90gcfJp8", "viewer": null}, "country_code": "NL", "language_code": "en", "entry_data": {"TagPage": [{"tag": {"name": "problems", "content_advisory": null, "media": {"nodes": [{"comments_disabled": false, "id": "1516762178404132116", "dimensions": {"height": 1080, "width": 1080}, "owner": {"id": "290529806"}, "thumbnail_src": "https://scontent.cdninstagram.com/t51.2885-15/s640x640/sh0.08/e35/18513982_160014291198948_1487080405596110848_n.jpg", "is_video": false, "code": "BUMnypEhqUU", "date": 1495032163, "display_src": "https://scontent.cdninstagram.com/t51.2885-15/e35/18513982_160014291198948_1487080405596110848_n.jpg", "caption": "Attempting to wear everything that's in my closet at least once... starting now?\npc: @vic.alario \n#idk #tuesday #mood #ootd #blue #striped #shirt #dress #dirty #white #brick #wall #fashion #outfit #shopaholic #problems #helpme #brokeforlife #ihavenothingtowear #hudsonyards #westside #nyc #life", "comments": {"count": 1}, "likes": {"count": 8}}, {"comments_disabled": false, "id": "1516760785425851931", "dimensions": {"height": 750, "width": 750}, "owner": {"id": "4168736037"}, "thumbnail_src": "https://scontent.cdninstagram.com/t51.2885-15/s640x640/sh0.08/e35/18513524_359389374459294_9061477754347716608_n.jpg", "is_video": false, "code": "BUMneXwjOYb", "date": 1495031997, "display_src": "https://scontent.cdninstagram.com/t51.2885-15/s750x750/sh0.08/e35/18513524_359389374459294_9061477754347716608_n.jpg", "caption": "\u270c\n#problems #goodlife #money #relax #rolex #dark #ilmnati #society", "comments": {"count": 2}, "likes": {"count": 3}}, {"comments_disabled": false, "id": "1516759187614097751", "dimensions": {"height": 1349, "width": 1080}, "owner": {"id": "6318461"}, "thumbnail_src": "https://scontent.cdninstagram.com/t51.2885-15/s640x640/sh0.08/e35/c0.134.1080.1080/18512620_1536771586356111_6438290774252584960_n.jpg", "is_video": false, "code": "BUMnHHrjGFX", "date": 1495031806, "display_src": "https://scontent.cdninstagram.com/t51.2885-15/e35/18512620_1536771586356111_6438290774252584960_n.jpg", "caption": "#biennaledivenezia #kikismith #problems #human #world", "comments": {"count": 0}, "likes": {"count": 9}}, {"comments_disabled": true, "id": "1516759129531599568", "dimensions": {"height": 360, "width": 640}, "owner": {"id": "974087501"}, "thumbnail_src": "https://scontent.cdninstagram.com/t51.2885-15/e15/c157.0.405.405/18580729_190728734782924_6334684785704697856_n.jpg", "is_video": true, "code": "BUMnGRlj8rQ", "date": 1495031799, "display_src": "https://scontent.cdninstagram.com/t51.2885-15/s640x640/e15/18580729_190728734782924_6334684785704697856_n.jpg", "video_views": 12, "caption": "\ud83d\ude30\u2600\ufe0f\u2744\ufe0f #vielzuwarm #problems #sun #hot #kitchen #lovemyjob #coldice #netterkollege #team #kitchenproblems #cuisine #heat #specialteam #fun #wolltedochnuressen @maitredecusine", "comments": {"count": 0}, "likes": {"count": 5}}, {"comments_disabled": false, "id": "1516758536204793702", "dimensions": {"height": 608, "width": 1080}, "owner": {"id": "930265200"}, "thumbnail_src": "https://scontent.cdninstagram.com/t51.2885-15/e35/c236.0.608.608/18513702_1687981828171773_2179029658803109888_n.jpg", "is_video": false, "code": "BUMm9pAhzdm", "date": 1495031729, "display_src": "https://scontent.cdninstagram.com/t51.2885-15/e35/18513702_1687981828171773_2179029658803109888_n.jpg", "caption": "These demons in me are dragging me down. I can't help the words that they say and I can't help that they come out to play. I'm sinking down and I see no way out. #imsinking #lifeishard #problems #demons #strugglingtolive #weightonmyshoulders", "comments": {"count": 0}, "likes": {"count": 0}}, {"comments_disabled": false, "id": "1516757626057347647", "dimensions": {"height": 750, "width": 750}, "owner": {"id": "986279121"}, "thumbnail_src": "https://scontent.cdninstagram.com/t51.2885-15/s640x640/sh0.08/e35/18513511_1873119239616443_5484959552396853248_n.jpg", "is_video": false, "code": "BUMmwZXg1I_", "date": 1495031620, "display_src": "https://scontent.cdninstagram.com/t51.2885-15/s750x750/sh0.08/e35/18513511_1873119239616443_5484959552396853248_n.jpg", "caption": "Curlyhair problems \ud83d\ude27\n#true #curlyhair #curls #hair #problems #beauty", "comments": {"count": 0}, "likes": {"count": 5}}, {"comments_disabled": false, "id": "1516757227162457019", "dimensions": {"height": 1080, "width": 1080}, "owner": {"id": "1427365"}, "thumbnail_src": "https://scontent.cdninstagram.com/t51.2885-15/s640x640/sh0.08/e35/18444257_1363886963697004_8812742106448658432_n.jpg", "is_video": false, "code": "BUMmql3hlO7", "date": 1495031573, "display_src": "https://scontent.cdninstagram.com/t51.2885-15/e35/18444257_1363886963697004_8812742106448658432_n.jpg", "caption": "\"A #positive #attitude may not solve all your #problems , but it will #annoy enough #people to make it worth the #effort .\" - #HermAlbright\n\nThis is the #real #motivation behind my #sunny disposition, y'all. \ud83d\ude00\u2600\ufe0f #true #flowers #daisies #art #quote #cheerful #love #happy #bubbly #glasshalffull #optimist", "comments": {"count": 0}, "likes": {"count": 2}}, {"comments_disabled": false, "id": "1516754712987303980", "dimensions": {"height": 1080, "width": 1080}, "owner": {"id": "396935836"}, "thumbnail_src": "https://scontent.cdninstagram.com/t51.2885-15/s640x640/sh0.08/e35/18444946_421879548193560_4562468446289264640_n.jpg", "is_video": false, "code": "BUMmGAXAgAs", "date": 1495031273, "display_src": "https://scontent.cdninstagram.com/t51.2885-15/e35/18444946_421879548193560_4562468446289264640_n.jpg", "caption": "Test results day. #lewisham #hospital #london #crohns #crohnsdisease #ctscan #bloodtest #stooltest #notverygood #gottogoback #c\u00e0mara #backpassage #invester #gate #bowel #boweldisease #problems #weightloss #noenergy #badpains #crohnssupport #crohnsandcolitis #crohnsandcolitisawareness #crohnslife #crohnssucks #imafighter #fingerscrossed #2weeks #time \ud83d\udc9c\ud83c\uddec\ud83c\udde7", "comments": {"count": 0}, "likes": {"count": 7}}, {"comments_disabled": false, "id": "1516753929676047331", "dimensions": {"height": 516, "width": 480}, "owner": {"id": "1790387217"}, "thumbnail_src": "https://scontent.cdninstagram.com/t51.2885-15/e35/c0.18.480.480/18580869_1057239011043319_7152183900138110976_n.jpg", "is_video": false, "code": "BUMl6m2BMPj", "date": 1495031180, "display_src": "https://scontent.cdninstagram.com/t51.2885-15/e35/18580869_1057239011043319_7152183900138110976_n.jpg", "caption": "Teruslah memfitnah tanpa menyelidiki lagi! #art #pic #problems #like4like", "comments": {"count": 0}, "likes": {"count": 11}}, {"comments_disabled": false, "id": "1516752226360836367", "dimensions": {"height": 809, "width": 1080}, "owner": {"id": "180789017"}, "thumbnail_src": "https://scontent.cdninstagram.com/t51.2885-15/s640x640/sh0.08/e35/c135.0.809.809/18512838_1712016712424546_3584145909249736704_n.jpg", "is_video": false, "code": "BUMlh0ghUEP", "date": 1495030977, "display_src": "https://scontent.cdninstagram.com/t51.2885-15/e35/18512838_1712016712424546_3584145909249736704_n.jpg", "caption": "I'm not surprised I don't quite fit.... #spanishfood \ud83d\ude05\n-\n-\n-\n#teacher #problems #spain #madrid #exploration #spainish #europe #adventure #lifeisgood #ig_spain #ig_europe #aroundtheworld #myjourney #wowplacestovisit #view #gf_spain #beautifuldestinations #travelersnotebook #placesearth #traveler #wanderlust #living_europe #wowfactor #springtime", "comments": {"count": 0}, "likes": {"count": 28}}, {"comments_disabled": false, "id": "1516751255380476380", "dimensions": {"height": 750, "width": 750}, "owner": {"id": "2139655255"}, "thumbnail_src": "https://scontent.cdninstagram.com/t51.2885-15/s640x640/sh0.08/e35/18513048_1571341339550956_731081486219870208_n.jpg", "is_video": false, "code": "BUMlTsNlMHc", "date": 1495030861, "display_src": "https://scontent.cdninstagram.com/t51.2885-15/s750x750/sh0.08/e35/18513048_1571341339550956_731081486219870208_n.jpg", "caption": "#be #grateful #for #small #things #big #things #and  #everything  #in #between .  #count #your #blessings\ud83d\ude07 #not #your #problems \ud83d\ude42\ud83d\ude42\ud83d\ude42\ud83d\ude42\ud83d\ude42\ud83d\ude42\ud83d\ude42\ud83d\ude42\ud83d\ude42", "comments": {"count": 0}, "likes": {"count": 10}}, {"comments_disabled": false, "id": "1516751039306860406", "dimensions": {"height": 1080, "width": 1080}, "owner": {"id": "1058822809"}, "thumbnail_src": "https://scontent.cdninstagram.com/t51.2885-15/s640x640/sh0.08/e35/18512501_1900622753545066_4680942215751532544_n.jpg", "is_video": false, "code": "BUMlQi-lwd2", "date": 1495030835, "display_src": "https://scontent.cdninstagram.com/t51.2885-15/e35/18512501_1900622753545066_4680942215751532544_n.jpg", "caption": "Honestly.\nIt's too much problems in my head now.\nFamily, Life and even Myself.\n\nTak tahu nak luah dekat siapa.?\nPenat dah nangis je.\n\n#headache #problems #stress #metalbreakdown #cry", "comments": {"count": 0}, "likes": {"count": 6}}, {"comments_disabled": false, "id": "1516750604389745871", "dimensions": {"height": 750, "width": 750}, "owner": {"id": "1552419140"}, "thumbnail_src": "https://scontent.cdninstagram.com/t51.2885-15/s640x640/sh0.08/e35/18512347_122276305011825_7059666340327456768_n.jpg", "is_video": false, "code": "BUMlKN7goTP", "date": 1495030783, "display_src": "https://scontent.cdninstagram.com/t51.2885-15/s750x750/sh0.08/e35/18512347_122276305011825_7059666340327456768_n.jpg", "caption": "\ud83d\udcde 514.576.5037 .\n.\n.\n.\n#call #text #bookonline #tissues #muscles #problems #knots #tension #pain #relief #body #sore #postgym #relax #massage #relaxation #spa #zen #massagetherapy #514 #montreal #westisland #amgtherapy", "comments": {"count": 0}, "likes": {"count": 10}}, {"comments_disabled": false, "id": "1516749017207264894", "dimensions": {"height": 1080, "width": 1080}, "owner": {"id": "368183627"}, "thumbnail_src": "https://scontent.cdninstagram.com/t51.2885-15/s640x640/sh0.08/e35/18382678_462673947408869_4652215352762040320_n.jpg", "is_video": false, "code": "BUMkzHwD9Z-", "date": 1495030594, "display_src": "https://scontent.cdninstagram.com/t51.2885-15/e35/18382678_462673947408869_4652215352762040320_n.jpg", "caption": "That moment when you finish like three exams but you already feel like you've done everything. Well, still got like 18 exams to go or something.\n\nTags: #gcse #problems #cafe #Nero #coffee #is #life #rainy #hair", "comments": {"count": 0}, "likes": {"count": 3}}, {"comments_disabled": false, "id": "1516748864551754164", "dimensions": {"height": 1080, "width": 1080}, "owner": {"id": "1525065381"}, "thumbnail_src": "https://scontent.cdninstagram.com/t51.2885-15/s640x640/sh0.08/e35/18513074_1829436284050537_8246920305965006848_n.jpg", "is_video": false, "code": "BUMkw5lFZm0", "date": 1495030576, "display_src": "https://scontent.cdninstagram.com/t51.2885-15/e35/18513074_1829436284050537_8246920305965006848_n.jpg", "caption": "#shopping#withmum#imboring#grey#black#darkcolors#omg#afterschool#likeforlike#follow4follow#likeforfollow#ilike#imshort#shortpeopleproblems#each#shirt#toobig#problems#tooskinny#icant#lol# \ud83d\ude23\ud83d\ude14\ud83d\ude4f\ud83d\ude48\ud83d\udc83\ud83d\ude34\ud83c\udf1f\ud83d\udc57\ud83d\udc5a\ud83d\udc56", "comments": {"count": 0}, "likes": {"count": 16}}, {"comments_disabled": false, "id": "1516748253391309225", "dimensions": {"height": 401, "width": 320}, "owner": {"id": "4722779427"}, "thumbnail_src": "https://scontent.cdninstagram.com/t51.2885-15/e35/c0.40.320.320/18445054_1081110221988508_6229656256743735296_n.jpg", "is_video": false, "code": "BUMkoAZFUmp", "date": 1495030503, "display_src": "https://scontent.cdninstagram.com/t51.2885-15/e35/18445054_1081110221988508_6229656256743735296_n.jpg", "caption": "\ud83d\udc65 #problems", "comments": {"count": 0}, "likes": {"count": 0}}, {"comments_disabled": false, "id": "1516747050849637099", "dimensions": {"height": 1080, "width": 1080}, "owner": {"id": "1753304946"}, "thumbnail_src": "https://scontent.cdninstagram.com/t51.2885-15/s640x640/sh0.08/e35/18513858_429782460716530_6556766871587127296_n.jpg", "is_video": false, "code": "BUMkWgcA5Lr", "date": 1495030360, "display_src": "https://scontent.cdninstagram.com/t51.2885-15/e35/18513858_429782460716530_6556766871587127296_n.jpg", "caption": "#wednesday#alittle#bad#i#have#had#enough#everything#wrong#problems#difficult#character#fuck#the#feelings#never#again#the#same#sentiment#black#reality", "comments": {"count": 2}, "likes": {"count": 26}}], "count": 1687354, "page_info": {"has_next_page": true, "end_cursor": "J0HWRxhYwAAAF0HWRxaWAAAAFiYA"}}, "top_posts": {"nodes": [{"id": "1516135309623861627", "dimensions": {"height": 539, "width": 480}, "owner": {"id": "516514799"}, "thumbnail_src": "https://scontent.cdninstagram.com/t51.2885-15/e35/c0.33.539.539/18513899_379823229079062_4592886160593780736_n.jpg", "is_video": false, "code": "BUKZQgBjqF7", "date": 1494957434, "display_src": "https://scontent.cdninstagram.com/t51.2885-15/e35/p480x480/18513899_379823229079062_4592886160593780736_n.jpg", "caption": "Takze sem vyrazila na Prikopy s obrim brichem a predstavou, ze v normalnich obchodech proste normalne koupim neco letniho, v cem doziju do porodu. Maxi saty nebo neco vid, dyt je toho vsude tri prdelky. Tak neni. Kostym Obelixe sem nakonec nechala v Mangu a sla na dort. Hele co tak jako nosite, kdyz zrovna nemate postavu etericky vily s neznym pupickem? Houstone, mame problem! #pregnant #problems #prdele #potrebuju #poradit", "comments": {"count": 354}, "likes": {"count": 13244}}, {"id": "1516437531188880978", "dimensions": {"height": 617, "width": 750}, "owner": {"id": "1632478879"}, "thumbnail_src": "https://scontent.cdninstagram.com/t51.2885-15/e35/c66.0.617.617/18444209_134159903798572_6002341487650537472_n.jpg", "is_video": false, "code": "BULd-ZylWZS", "date": 1494993462, "display_src": "https://scontent.cdninstagram.com/t51.2885-15/e35/18444209_134159903798572_6002341487650537472_n.jpg", "caption": "Digital artist problems", "comments": {"count": 145}, "likes": {"count": 7147}}, {"id": "1516297915752413902", "dimensions": {"height": 640, "width": 640}, "owner": {"id": "1433489086"}, "thumbnail_src": "https://scontent.cdninstagram.com/t51.2885-15/e35/18444948_221552388340046_7896738209139261440_n.jpg", "is_video": false, "code": "BUK-OuyFnrO", "date": 1494976819, "display_src": "https://scontent.cdninstagram.com/t51.2885-15/e35/18444948_221552388340046_7896738209139261440_n.jpg", "caption": "\u2022\u2022\u2022\u2022\u2022\u2022\u2022\u2022\u2022\u2022\u2022\u2022\u2022\u2022\u2022\u2022\u2022\u2022\u2022\u2022\u2022\u2022\u2022\u2022\nTag someone who can relate \u2022\u2022\u2022\u2022\u2022\u2022\u2022\u2022\u2022\u2022\u2022\u2022\u2022\u2022\u2022\u2022\u2022\u2022\u2022\u2022\u2022\u2022\u2022\u2022\u2022\u2022\u2022\u2022\u2022\u2022\u2022\u2022\u2022\u2022\u2022\u2022\u2022\u2022\u2022\u2022\u2022\u2022\u2022\u2022\nWrestler Problems\n#wrestle #wrestler #wrestling\n#problem #problems #wrestlerproblems #wrestlingproblems #followforcommonproblemswrestlershave #theme\n\u2022\u2022\u2022\u2022\u2022\u2022\u2022\u2022\u2022\u2022\u2022\u2022\u2022\u2022\u2022\u2022\u2022\u2022\u2022\u2022\u2022\u2022\u2022\u2022\u2022\u2022\u2022\u2022\u2022\u2022\u2022\u2022\u2022\u2022\u2022\u2022\u2022\u2022\u2022\u2022\u2022\u2022\u2022\u2022\n\u2022\u2022\u2022\u2022\u2022\u2022\u2022\u2022\u2022\u2022\u2022\u2022\u2022\u2022\u2022\u2022\u2022\u2022\u2022\u2022\u2022\u2022\u2022\u2022\u2022\u2022\u2022\u2022\u2022\u2022\u2022\u2022\u2022\u2022\u2022\u2022\u2022\u2022\u2022\u2022\u2022\u2022\u2022\u2022\nDo you want to help us get to 25k followers and beyond? Do you want to see your photos, problems or suggestions on our page? If so, send your ideas, suggestions, problems or photos to our DM, or to our Snapchat (beasley1219)", "comments": {"count": 79}, "likes": {"count": 2405}}, {"id": "1516352279350756421", "dimensions": {"height": 677, "width": 750}, "owner": {"id": "1450407197"}, "thumbnail_src": "https://scontent.cdninstagram.com/t51.2885-15/s640x640/sh0.08/e35/c36.0.677.677/18513105_260869834385437_5846093059913154560_n.jpg", "is_video": false, "code": "BULKl01DkRF", "date": 1494983299, "display_src": "https://scontent.cdninstagram.com/t51.2885-15/e35/18513105_260869834385437_5846093059913154560_n.jpg", "caption": "Shiiiieeeettt... #Baseball #BushLeague #Degenerate #Ballplayer #School #Grades #Eligibility #Problems", "comments": {"count": 11}, "likes": {"count": 1077}}, {"id": "1515395942680043235", "dimensions": {"height": 360, "width": 640}, "owner": {"id": "12020877"}, "thumbnail_src": "https://scontent.cdninstagram.com/t51.2885-15/e15/c140.0.360.360/18382689_808405225984581_1722337423918104576_n.jpg", "is_video": true, "code": "BUHxJS5gx7j", "date": 1494869295, "display_src": "https://scontent.cdninstagram.com/t51.2885-15/e15/18382689_808405225984581_1722337423918104576_n.jpg", "video_views": 33115, "caption": "#problems now on youtube LINK IN MY BIO", "comments": {"count": 374}, "likes": {"count": 9987}}, {"id": "1516123266165521681", "dimensions": {"height": 1080, "width": 1080}, "owner": {"id": "182560459"}, "thumbnail_src": "https://scontent.cdninstagram.com/t51.2885-15/s640x640/sh0.08/e35/18513187_213974245774815_4058896724972797952_n.jpg", "is_video": false, "code": "BUKWhPrgD0R", "date": 1494955999, "display_src": "https://scontent.cdninstagram.com/t51.2885-15/e35/18513187_213974245774815_4058896724972797952_n.jpg", "caption": "#PROBLEMS", "comments": {"count": 18}, "likes": {"count": 2173}}, {"id": "1515364426269330709", "dimensions": {"height": 674, "width": 1080}, "owner": {"id": "334204066"}, "thumbnail_src": "https://scontent.cdninstagram.com/t51.2885-15/s640x640/sh0.08/e35/c203.0.674.674/18513111_1933400160280430_8769199298505080832_n.jpg", "is_video": false, "code": "BUHp-q9DA0V", "date": 1494865538, "display_src": "https://scontent.cdninstagram.com/t51.2885-15/e35/18513111_1933400160280430_8769199298505080832_n.jpg", "caption": "#PROBLEMS JUST DROPPED! Link in my bio! \ud83d\udd25\ud83d\udd25\ud83d\udd25\ud83d\udd25SALUTE TO MY SQUAD", "comments": {"count": 30}, "likes": {"count": 3047}}, {"id": "1515901586773077677", "dimensions": {"height": 607, "width": 1080}, "owner": {"id": "1381603152"}, "thumbnail_src": "https://scontent.cdninstagram.com/t51.2885-15/e15/c236.0.607.607/18444234_1818629071798133_7056748880712433664_n.jpg", "is_video": true, "code": "BUJkHYqD26t", "date": 1494929572, "display_src": "https://scontent.cdninstagram.com/t51.2885-15/s1080x1080/e15/fr/18444234_1818629071798133_7056748880712433664_n.jpg", "video_views": 8710, "caption": "Snow Tha Product contin\u00faa lanzando material de manera in\u00e9dita sin prisa pero sin pausa. No ha anunciado ning\u00fan proyecto, pero la asiduidad con la que los presenta hace indicar a sus seguidores que no tardar\u00e1 en hacerlo. \u2018Problems\u2019 es el t\u00edtulo del \u00faltimo clip producido por Brown Royal y realizado por Woke Productions. Disfr\u00fatalo ya con las primeras novedades del d\u00eda.\n\nLink en bio.\n\n#SnowThaProduct #WokeProductions #BrownRoyal #Problems @snowthaproduct", "comments": {"count": 33}, "likes": {"count": 1123}}, {"id": "1516687647191791813", "dimensions": {"height": 750, "width": 750}, "owner": {"id": "1605588834"}, "thumbnail_src": "https://scontent.cdninstagram.com/t51.2885-15/s640x640/sh0.08/e35/18579754_1429535813774896_5468490663509098496_n.jpg", "is_video": false, "code": "BUMW2EeFvjF", "date": 1495023278, "display_src": "https://scontent.cdninstagram.com/t51.2885-15/s750x750/sh0.08/e35/18579754_1429535813774896_5468490663509098496_n.jpg", "caption": "#20170517\n\u6b61\u8fce\u5149\u81e8 \u5168\u5bb6\u5c31\u662f\u4f60\u5bb6\n\u5443\u62b1\u6b49\u9019\u88e1\u662fok\u2026\u2026\n-\n\u554f\u984c\u4e0d\u4e00\u6b21\u8655\u7406\u597d\n\u554f\u984c\u6c38\u9060\u90fd\u5728\u8ddf\u4f60\u63ee\u624b\n\u8aaa\u597d\u4e86\u5c31\u8981\u4e00\u8d77\u6539\u5584\u4e00\u8d77\u52aa\u529b\n\u52a0\u6cb9\u52a0\u6cb9\ud83d\ude09\n#instagood #love #ootd #follow #like #girl #ok #last #one #good #problems #trouble #cheers", "comments": {"count": 8}, "likes": {"count": 793}}]}}}]}, "gatekeepers": {"bn": true, "ld": true, "pl": true}, "qe": {"ebd": {"g": "", "p": {}}, "create": {"g": "", "p": {}}, "disc": {"g": "", "p": {}}, "feed": {"g": "", "p": {}}, "gql": {"g": "", "p": {}}, "su_universe": {"g": "", "p": {}}, "us": {"g": "", "p": {}}, "us_li": {"g": "", "p": {}}, "nav": {"g": "", "p": {}}, "nav_lo": {"g": "", "p": {}}, "poe": {"g": "try_email_and_phone_login_control_05", "p": {"show_phone_or_email_text": "false", "try_email_and_phone_login": "false"}}, "pm": {"g": "", "p": {}}, "profile": {"g": "", "p": {}}, "deact": {"g": "", "p": {}}, "sidecar": {"g": "", "p": {}}, "ufi": {"g": "", "p": {}}, "ufi_loggedout": {"g": "test_20170411", "p": {"is_enabled": "true"}}, "video": {"g": "", "p": {}}}, "hostname": "www.instagram.com", "display_properties_server_guess": {"pixel_ratio": 1.5, "viewport_width": 360}, "environment_switcher_visible_server_guess": true, "platform": "web", "probably_has_app": false, "show_app_install": true}